setup.py
gisting_test/__init__.py
gisting_test.egg-info/PKG-INFO
gisting_test.egg-info/SOURCES.txt
gisting_test.egg-info/dependency_links.txt
gisting_test.egg-info/top_level.txt
gisting_test/src/__init__.py
gisting_test/src/arguments.py
gisting_test/src/benchmarking.py
gisting_test/src/compress.py
gisting_test/src/generation_utils.py
gisting_test/src/gist_caching.py
gisting_test/src/gist_llama.py
gisting_test/src/gist_t5.py
gisting_test/src/integrations.py
gisting_test/src/metrics.py
gisting_test/src/train.py
gisting_test/src/trainer_seq2seq.py
gisting_test/src/utils.py
gisting_test/src/weight_diff.py
gisting_test/src/data/__init__.py
gisting_test/src/data/gist.py
gisting_test/src/data/utils.py