Metadata-Version: 2.1
Name: gisting-test
Version: 0.1.7
Summary: Test version for gisting
Home-page: https://github.com/jayelm/gisting
Author: Owais Zahid
License: UNKNOWN
Platform: UNKNOWN
Classifier: Natural Language :: English
Classifier: Programming Language :: Python :: 3
